seqslab/README.md
seqslab/__init__.py
seqslab/cli.py
seqslab/context.py
seqslab/exceptions.py
seqslab/plugin.py
seqslab/session_logger.py
seqslab/settings.py
seqslab/statusbar.py
seqslab/usage_logger.py
seqslab/auth/__init__.py
seqslab/auth/azuread.py
seqslab/auth/commands.py
seqslab/drs/__init__.py
seqslab/drs/commands.py
seqslab/drs/api/__init__.py
seqslab/drs/api/azure.py
seqslab/drs/api/base.py
seqslab/drs/api/common.py
seqslab/drs/api/template.py
seqslab/drs/internal/__init__.py
seqslab/drs/internal/aiocopy.py
seqslab/drs/internal/common.py
seqslab/drs/internal/utils.py
seqslab/drs/storage/__init__.py
seqslab/drs/storage/azure.py
seqslab/drs/storage/base.py
seqslab/drs/tests/__init__.py
seqslab/drs/tests/tests.py
seqslab/drs/utils/__init__.py
seqslab/drs/utils/biomimetype.py
seqslab/drs/utils/progressbar.py
seqslab/organization/__init__.py
seqslab/organization/commands.py
seqslab/organization/resource/__init__.py
seqslab/organization/resource/base.py
seqslab/role/__init__.py
seqslab/role/commands.py
seqslab/role/internal/__init__.py
seqslab/role/internal/common.py
seqslab/role/resource/__init__.py
seqslab/role/resource/azure.py
seqslab/role/resource/base.py
seqslab/role/tests/__init__.py
seqslab/role/tests/tests.py
seqslab/runsheet/__init__.py
seqslab/runsheet/runsheet.py
seqslab/tests/__init__.py
seqslab/tests/util.py
seqslab/trs/__init__.py
seqslab/trs/commands.py
seqslab/trs/internal/__init__.py
seqslab/trs/internal/utils.py
seqslab/trs/register/__init__.py
seqslab/trs/register/azure.py
seqslab/trs/register/base.py
seqslab/trs/register/common.py
seqslab/trs/register/template.py
seqslab/trs/resource/__init__.py
seqslab/trs/resource/azure.py
seqslab/trs/resource/base.py
seqslab/trs/resource/common.py
seqslab/trs/template/__init__.py
seqslab/trs/template/base.py
seqslab/trs/template/template.py
seqslab/trs/tests/__init__.py
seqslab/trs/tests/tests.py
seqslab/user/__init__.py
seqslab/user/commands.py
seqslab/user/internal/__init__.py
seqslabcli-3.2.0.post1.dist-info/LICENSE
seqslabcli-3.2.0.post1.dist-info/METADATA
seqslabcli-3.2.0.post1.dist-info/WHEEL
seqslabcli-3.2.0.post1.dist-info/entry_points.txt
seqslabcli-3.2.0.post1.dist-info/top_level.txt
seqslabcli-3.2.0.post1.dist-info/zip-safe
seqslabcli-3.2.0.post1.dist-info/RECORD
