Metadata-Version: 2.1
Name: seqslabcli
Version: 3.2.0.post1
Summary: Seqslab CLI
Home-page: https://github.com/AnomeGAP/seqslab-cli
Author: Jia-You Lin
Author-email: jiayou.lin@atgenomix.com
License: MIT license
Platform: UNKNOWN
Classifier: Intended Audience :: Developers
Classifier: License :: OSI Approved :: MIT License
Classifier: Operating System :: OS Independent
Classifier: Programming Language :: Python
Classifier: Programming Language :: Python :: 3.8
Classifier: Programming Language :: Python :: 3.9
Requires-Python: >=3.8
Requires-Dist: pip (>=22.0.4)
Requires-Dist: cryptography (==38.0.3)
Requires-Dist: jeepney (==0.7.1)
Requires-Dist: secretstorage (==3.3.2)
Requires-Dist: dbus-python (==1.2.16)
Requires-Dist: keyring (==23.5.0)
Requires-Dist: numba (==0.54.1)
Requires-Dist: python-nubia (==0.2b5)
Requires-Dist: msal (==1.17.0)
Requires-Dist: tenacity (==8.0.1)
Requires-Dist: aiofiles (==0.8.0)
Requires-Dist: aiohttp[speedups] (==3.8.1)
Requires-Dist: aioretry (==5.0.2)
Requires-Dist: uvloop (==0.16.0)
Requires-Dist: arrow (==1.2.2)
Requires-Dist: yarl (==1.4.2)
Requires-Dist: requests-toolbelt (==0.9.1)
Requires-Dist: sample-sheet (==0.12.0)
Requires-Dist: PyJWT (==2.4.0)
Requires-Dist: django-environ (==0.8.1)
Requires-Dist: validators (==0.19.0)
Requires-Dist: pydot (==1.4.2)
Requires-Dist: orjson (==3.7.8)
Requires-Dist: pydantic (~=1.8.2)
Requires-Dist: aiohttp-retry (==2.8.3)
